{
  "document_name": "Fatca.jpeg",
  "document_type": "FATCA Annexure Form",
  "is_handwritten": true,
  "ocr_text": "HDFC\nNbht  4921011602\nCNa\nLife\nANNEXURE FORM\nJunder Section 285BAofthe Income Tax Act, 1961)\nSofutho\nve jitol\n(Informotion required forrcporting\nindwvnhnl\n(Froposct /rolicyholder/ Annuitant) os applicoble\nThis form Is ta bc hlked by on\nScction E Idcntihcation Detalls (Dleasc tclfondcomleteos opproprioto)\nPolny No:\n[oiol2L\nc) Customer I0 (To be filled by HDF\u20ac Life):_\n6) Namc ol the\nFronoscr /Policyholder/Annuitant:\nSection 2: Dcclaration of Tax Residency\nof taxresidence (as per section 6 of the Income Tax Act: 1961)\nPlcase indicatc cOuntly \"\nAny othcr country\nOnly hndia\nb) India and any other country\nsclected option (bJor (c) you are required to provide the details and documents a5 mentioned belmbe\nequivalent in each country is given below; or /\nyouhave\ncountryicountries and my Tax Identification Number (TINVfunctional\nthe purpose 0f taration;\nJm.\nresident in the following\nthan one)\"\nTIN/functional equivalent is unavailable (fiIl details of all countries of tax residence f more\nhae indicated that ?\nDocuments provided\nIdentification Numbcre\nTIN/ Functional equivalent\n(self-atlested copyor certlicate ?  residenceMTIN/\nCountry/Countneso\nTax \nissuing country\nFunction)/ equivalent) \ntx residency\nFunctional equivalent\nLodc\nPQED Zo5LR\nLrdeo\nPanCad\nTIN\nFunctlonal equlvalent tor all the countriles listedin the table:\nDocuments rcquircd: Plcase submit a self attested copy of either Certificate of Residete or\nSection3:\nFurther Individual Identification details\nBeelE:\nc) Place of birth:_\nWesdBeky\na) Father s Name:\nAxjun\nKuny b) Spouses Name:\npdlea\ne) Nationality:\nLndean\nOccupation:_\nSalacieal\nd) Country of binth:\nTerms\nConditions for thc\nProposcr/Policyholder/Annuitant\nIcentify that\nsection28S8A of the Income Tax Act 1961;read with Rules HLAF toLlaHof the Incomeired\nThave understood the information requirements of this Annexure (read alongwith\ninformationin the documentary evidence provided by me are asrequired\nRules,1962) The information providedin the Proposal Form and its supporting Annexures,as wellas\nunder the aforesaid section and applicable rules:\ndocumentary evidence provided by me are true; correct and complete to the\nThe information provided by me in the Proposal Form; its supporting Annexures 35 'ell as In the\nthe assessmentycategorisation of the policy held by me (here in after\nbest Ofony knowiedge and belief and that ihave not withheld any material information tha9nay affere\nreferred t0 as the Account )& =\nReportable Account (a5 defined under Income Tax Rules.1962) or otherwise:\ncommunicate and process Information relating t0\n{permitauthori e HDFC Lite Insurance Company Limited (hereinafter referred a5 the\"Comtian ) tocoeleet sitotc\ntransfer and disclosure between them\nMiated above and all transactions therein by the Company and any ofit5 affiliates wherever situated includineshoring\nmy Accouni a;\noutside India of any confidential information for compliance with any law or regulation whether domestic or foreigg;_\nandto the autoritie:\nand/or 5\nprovided by me in the Proposal Form Its supporting Annexures as well as Inthe documentary evidence for\nTunderstand that the Company i5 relying on the information\nthat the Companyis not able to offer any taxadvice on FATCA/CRSor its impacton me  Ishall\npurposeof determining mystatusin compliancewith FATCACRS |alsounderstand\nscekad icetrom\nprofessional tar advisor for any questionson taxation\nof change\nchanges that may take place In the information provided Inthe Proposal Form;\n(undertake the responsibility to declare and disclse within 30days from the\nany\nincorrect and to provide fresh self-certification along with\nit supporting Annexures as well a5 in the documentary evidence prozided by me,\nany certification becomes\ndocumientary evidence_\nmaterial fact known t0 me, now or in future, may Invalidate my applicatlon ad the Corpany would be within its right t0 put\nako agree that my failure tO disclose any\nany authority designated by the Governmentof India (GOI) /IRDAI for the purposeor takc\nrestrictions in the operationsof my Accountor closeitor reporttoanyregulatorand/or\nOchionacnionaS may be deemed appropriate by the Company if the deficiency is not remedied by mevrithin the stipulatedperiod\nan}\nang manoedecgeethap hertompany shalhave theright and authority to carry out investigations from the information available Inpublic domain for confirming\nThereey accepl\nthe information provided by me to the Company:\nfurnish suchinformation and/or documents asthe Company may require from time to time on account of any change in law either in India or abroad in the subject\nIakpagree [0\nTTnal nccennify\ndefend and nold harmless the Company and its officers\ndirectors\nemployees, representatives from and against any liability or loss that may arisc to the\nCompany on account of providing incorrect or incomplete information:\nNamc & Signature of the\nProposcr/Policyholder/Annuitant:\nAzhok\nSionheRE\nDate\n28Lu442n;\nAn\nPlace;\nAleskBekz~\nHDFC Lile Insurance Company Limited (HIDFC Life) CIN: L6SH [OMHZOOOPLCI28245. IRDAI\nRegistration No. 10L.\nRred_\nOft: [Jd, Fl Lodha Excelus, Apollo Mill: Cornpound NM:Joshi Marg Mahaluxmi, Mumbai\n400 0m.\nFor Office use only (to bc filled by HDI \u20ac Uife employe\nDetail: of the HDFC Life employee collecting the Annexure\nName:\nDesignation:\nEmployee Code:\nLocation:\nFo\"\n(MN)\nDos\nand\nthe\ndate \nOf If",
  "extracted_data": {
    "Policy Number": {
      "value": "4921011602",
      "confidence": 1.0,
      "validation_passed": true
    },
    "TIN / PAN": {
      "value": "PQED Zo5LR",
      "confidence": 0.85,
      "validation_passed": true
    },
    "Father's Name": {
      "value": "Axjun",
      "confidence": 0.95,
      "validation_passed": true
    },
    "Place of Birth": {
      "value": "WesdBeky",
      "confidence": 0.85,
      "validation_passed": true
    },
    "Nationality": {
      "value": "Lndean",
      "confidence": 0.9,
      "validation_passed": true
    }
  }
}